cli_options/__init__.py
cli_options/__main__.py
cli_options/main.py
cli_options-0.2.1.dist-info/METADATA
cli_options-0.2.1.dist-info/WHEEL
cli_options-0.2.1.dist-info/entry_points.txt
cli_options-0.2.1.dist-info/RECORD
